scrapy_folder_tree/__init__.py
scrapy_folder_tree/config.py
scrapy_folder_tree/pipelines.py
scrapy_folder_tree/trees/__init__.py
scrapy_folder_tree/trees/date.py
scrapy_folder_tree/trees/hash.py
scrapy_folder_tree-0.1.3.dist-info/LICENSE
scrapy_folder_tree-0.1.3.dist-info/WHEEL
scrapy_folder_tree-0.1.3.dist-info/METADATA
scrapy_folder_tree-0.1.3.dist-info/RECORD
