Metadata-Version: 2.1
Name: scrapy-folder-tree
Version: 0.1.3
Summary: A scrapy pipeline which stores files using folder trees.
Home-page: https://github.com/sp1thas/scrapy-folder-tree
License: MIT
Keywords: scrapy,scrapy-files-structure,scrapy-folder-tree,folder-tree
Author: Panagiotis Simakis
Maintainer: Panagiotis Simakis
Requires-Python: >=3.7,<4.0
Classifier: Development Status :: 4 - Beta
Classifier: Framework :: Pytest
Classifier: License :: OSI Approved :: MIT License
Classifier: Natural Language :: English
Classifier: Natural Language :: Greek
Classifier: Operating System :: OS Independent
Classifier: Programming Language :: Python :: 3
Classifier: Programming Language :: Python :: 3.10
Classifier: Programming Language :: Python :: 3.6
Classifier: Programming Language :: Python :: 3.7
Classifier: Programming Language :: Python :: 3.8
Classifier: Programming Language :: Python :: 3.9
Classifier: Topic :: Software Development :: Libraries :: Python Modules
Requires-Dist: Scrapy (>=2.5.1,<3.0.0)
Project-URL: Bug Tracker, https://github.com/sp1thas/scrapy-folder-tree/issues
Project-URL: Repository, https://github.com/sp1thas/scrapy-folder-tree
